eve_to_sqlite/__init__.py
eve_to_sqlite/cli.py
eve_to_sqlite-1.0.0.dist-info/LICENSE
eve_to_sqlite-1.0.0.dist-info/METADATA
eve_to_sqlite-1.0.0.dist-info/WHEEL
eve_to_sqlite-1.0.0.dist-info/entry_points.txt
eve_to_sqlite-1.0.0.dist-info/top_level.txt
eve_to_sqlite-1.0.0.dist-info/RECORD
