Metadata-Version: 2.1
Name: eve-to-sqlite
Version: 1.0.0
Summary: Convert Eve measurement exports to a SQLite database
Home-page: https://github.com/badboy/eve-to-sqlite
Author: Jan-Erik Rediger
License: Apache License, Version 2.0
Platform: UNKNOWN
License-File: LICENSE
Requires-Dist: sqlite-utils (>=2.7.2)
Requires-Dist: openpyxl
